{
  "sections": {
    "page-rich-text-image": {
      "type": "page-rich-text-image",
      "settings": {
        "subheading": "",
        "title": "Kris Craig",
        "image": "shopify:\/\/shop_images\/KrisCraig2_Page_1200x1080_b404c486-c25c-4c1e-8f09-9e3d9f99cd4a.png",
        "image_position": "left",
        "content": "",
        "height": "6' 8\"",
        "weight": "270 lbs",
        "DOB": "October 1, 1989",
        "residence": "Orlando, FL",
        "facebook_url": "",
        "instagram_url": "https:\/\/www.instagram.com\/accounts\/login\/?next=\/kris_craig33\/",
        "youtube_url": "",
        "pinterest_url": "",
        "snapchat_url": "",
        "twitter_url": "",
        "tumblr_url": "",
        "google_plus_url": "",
        "vimeo_url": "",
        "linkedin_url": ""
      }
    },
    "main": {
      "type": "Athlete24",
      "settings": {
        "title1": "EXPERIENCE",
        "title2": "INSTAGRAM"
      }
    },
    "page-featured-video": {
      "type": "page-featured-video",
      "settings": {
        "section_size": "large",
        "text_color": "#ffffff",
        "subheading": "",
        "title": "Your video",
        "video_url": ""
      }
    }
  },
  "order": [
    "page-rich-text-image",
    "main",
    "page-featured-video"
  ]
}